komo/__init__.py
komo/api_client.py
komo/core.py
komo/printing.py
komo/types.py
komo/version.py
komo/agent/__init__.py
komo/agent/core.py
komo/aws/__init__.py
komo/aws/connect.py
komo/cli/__init__.py
komo/cli/cli.py
komo/cli/cmd_login.py
komo/cli/cmd_update.py
komo/cli/utils.py
komo/cli/agent/__init__.py
komo/cli/agent/agent.py
komo/cli/agent/cmd_download_workdir.py
komo/cli/agent/cmd_run.py
komo/cli/agent/cmd_run_service_replica.py
komo/cli/agent/cmd_setup.py
komo/cli/agent/cmd_setup_and_run.py
komo/cli/agent/cmd_setup_and_run_service_replica.py
komo/cli/agent/cmd_setup_machine.py
komo/cli/agent/cmd_setup_service_replica.py
komo/cli/aws/__init__.py
komo/cli/aws/aws.py
komo/cli/aws/cmd_connect.py
komo/cli/job/__init__.py
komo/cli/job/cmd_launch.py
komo/cli/job/cmd_list.py
komo/cli/job/cmd_logs.py
komo/cli/job/cmd_ssh.py
komo/cli/job/cmd_terminate.py
komo/cli/job/job.py
komo/cli/lambda_labs/__init__.py
komo/cli/lambda_labs/cmd_connect.py
komo/cli/lambda_labs/lambda_labs.py
komo/cli/machine/__init__.py
komo/cli/machine/cmd_launch.py
komo/cli/machine/cmd_list.py
komo/cli/machine/cmd_notebook.py
komo/cli/machine/cmd_setup_logs.py
komo/cli/machine/cmd_ssh.py
komo/cli/machine/cmd_terminate.py
komo/cli/machine/cmd_vscode.py
komo/cli/machine/machine.py
komo/cli/service/__init__.py
komo/cli/service/cmd_launch.py
komo/cli/service/cmd_list.py
komo/cli/service/cmd_terminate.py
komo/cli/service/service.py
komo/lambda_labs/__init__.py
komo/lambda_labs/connect.py
komo-0.2.53.dist-info/METADATA
komo-0.2.53.dist-info/WHEEL
komo-0.2.53.dist-info/entry_points.txt
komo-0.2.53.dist-info/top_level.txt
komo-0.2.53.dist-info/RECORD
