Metadata-Version: 2.1
Name: komo
Version: 0.2.53
Summary: Komodo AI CLI
Home-page: https://github.com/komodoai/komo
Author: Komodo AI
Author-email: anish@komodo.io
License: BSD
Platform: any
Classifier: Development Status :: 4 - Beta
Classifier: Environment :: Console
Classifier: Intended Audience :: Developers
Classifier: License :: OSI Approved :: BSD License
Classifier: Operating System :: POSIX
Classifier: Operating System :: MacOS
Classifier: Operating System :: Unix
Classifier: Operating System :: Microsoft :: Windows
Classifier: Programming Language :: Python
Classifier: Programming Language :: Python :: 2
Classifier: Programming Language :: Python :: 3
Classifier: Topic :: Software Development :: Libraries :: Python Modules
Requires-Python: >=3.8.0
Requires-Dist: click~=8.1.7
Requires-Dist: pyyaml~=6.0.1
Requires-Dist: requests~=2.31.0
Requires-Dist: boto3~=1.34.51
Requires-Dist: tabulate~=0.9.0
Requires-Dist: ws4py~=0.5.1
Requires-Dist: textwrap3~=0.9.2
Requires-Dist: retry~=0.9.2
Requires-Dist: pydantic~=2.7.3
Requires-Dist: pyjwt~=2.8.0
Requires-Dist: tenacity~=8.5.0
Requires-Dist: packaging~=24.1
Requires-Dist: sentry-sdk~=2.12.0
